[{"gva_id": 2112607, "incident_name": "", "start_date": "2021-09-10", "end_date": "", "place_type": "gas station", "place_name": "BP", "address": "135 University Ave SW", "city": "Atlanta", "state": "GA", "postal_code": "30315", "congressional": 5, "state_senate": 36, "state_house": 58, "deaths": 0, "wounded": 1, "location": {"type": "Point", "coordinates": [33.7219, -84.3926]}, "sources": [{"url": "https://www.ajc.com/news/3-sought-in-mans-shooting-outside-sw-atlanta-gas-station/Q3KTKYDHQ5DODC3HHYTK2QLHPY/", "isbn": "", "issn": "", "doi": "", "pmid": "", "sici": "", "type": "website", "title": "3 sought in man\u2019s shooting outside SW Atlanta gas station", "author": "Shaddi Abusaid", "organization": "The Atlanta Journal-Constitution", "first_published": "2021-09-10", "last_updated": ""}], "types": []}, {"gva_id": 2002687, "incident_name": "", "start_date": "2021-05-12T01:11Z", "end_date": "", "place_type": "residence", "place_name": "", "address": "3600 block of Ridgeside Rd", "city": "Chattanooga", "state": "TN", "postal_code": "37411", "congressional": 3, "state_senate": 10, "state_house": 28, "deaths": 2, "wounded": 1, "location": {"type": "Point", "coordinates": [35.0314, -85.2423]}, "sources": [{"url": "https://www.wrcbtv.com/story/43877410/cpd-investigating-tripleshooting-on-gillespie-road-separate-shooting-on-campbell-street", "isbn": "", "issn": "", "doi": "", "pmid": "", "sici": "", "type": "website", "title": "UPDATE: CPD investigating triple-shooting on Ridgeside Road, assault on Campbell Street", "author": "WRCB Staff", "organization": "WRCB Channel 3 St Productions", "first_published": "2019-05-12T01:30Z", "last_updated": "2019-05-13T18:43Z"}, {"url": "https://www.wrcbtv.com/story/43884092/two-killed-one-injured-in-ridgeside-road-shooting-chattanooga-pd-says", "isbn": "", "issn": "", "doi": "", "pmid": "", "sici": "", "type": "", "title": "", "author": "", "organization": "", "first_published": "", "last_updated": ""}], "types": []}, {"gva_id": 2002672, "incident_name": "", "start_date": "2021-05-12T23:40Z", "end_date": "", "place_type": "residence", "place_name": "", "address": "1026 Dewey Ave", "city": "New Castle", "state": "PA", "postal_code": "16101", "congressional": 16, "state_senate": 47, "state_house": 9, "deaths": 2, "wounded": 1, "location": {"type": "Point", "coordinates": [41.0082, -80.3254]}, "sources": [{"url": "https://www.wtae.com/article/new-castle-reported-shooting/36414118#", "isbn": "", "issn": "", "doi": "", "pmid": "", "sici": "", "type": "", "title": "", "author": "", "organization": "", "first_published": "", "last_updated": ""}, {"url": "https://www.wpxi.com/news/top-stories/police-2-killed-suspect-custody-new-castle-shooting/PYI3U4AGNFFOJNPDIVEE3ZSVAI/", "isbn": "", "issn": "", "doi": "", "pmid": "", "sici": "", "type": "", "title": "", "author": "", "organization": "", "first_published": "", "last_updated": ""}, {"url": "https://www.ncnewsonline.com/news/local_news/two-dead-in-triple-shooting/article_ae3a234e-d75b-5ee4-ba3d-5efe38082924.html", "isbn": "", "issn": "", "doi": "", "pmid": "", "sici": "", "type": "", "title": "", "author": "", "organization": "", "first_published": "", "last_updated": ""}, {"url": "https://www.ncnewsonline.com/news/local_news/police-suspect-tried-to-escape-after-shootings/article_6460901d-4173-50f1-8aeb-85aac02c05e9.html", "isbn": "", "issn": "", "doi": "", "pmid": "", "sici": "", "type": "", "title": "", "author": "", "organization": "", "first_published": "", "last_updated": ""}], "types": ["domestic violence"]}, {"gva_id": 2002269, "incident_name": "", "start_date": "2021-05-12T20:15Z", "end_date": "", "place_type": "store", "place_name": "", "address": "5500 block of Kingsessing Ave", "city": "Philadelphia", "state": "PA", "postal_code": "19143", "congressional": 5, "state_senate": 8, "state_house": 191, "deaths": 1, "wounded": 3, "location": {"type": "Point", "coordinates": [39.9368, -75.2235]}, "sources": [{"url": "https://6abc.com/gunman-opens-fire-on-philly-vigil-kingsessing-avenue-shooting-philadelphia-today/10624736/", "isbn": "", "issn": "", "doi": "", "pmid": "", "sici": "", "type": "", "title": "", "author": "", "organization": "", "first_published": "", "last_updated": ""}, {"url": "https://www.fox29.com/news/kingsessing-shooting-leaves-1-dead-3-others-injured-police-say", "isbn": "", "issn": "", "doi": "", "pmid": "", "sici": "", "type": "", "title": "", "author": "", "organization": "", "first_published": "", "last_updated": ""}, {"url": "https://www.nbcphiladelphia.com/news/local/gunman-shoots-at-least-3-people-in-southwest-philadelphia/2812204/", "isbn": "", "issn": "", "doi": "", "pmid": "", "sici": "", "type": "", "title": "", "author": "", "organization": "", "first_published": "", "last_updated": ""}, {"url": "https://philadelphia.cbslocal.com/2021/05/13/man-killed-southwest-philadelphia-quadruple-shooting/", "isbn": "", "issn": "", "doi": "", "pmid": "", "sici": "", "type": "", "title": "", "author": "", "organization": "", "first_published": "", "last_updated": ""}, {"url": "https://triblive.com/news/pennsylvania/gunman-opens-fire-at-memorial-site-killing-man-wounding-3/", "isbn": "", "issn": "", "doi": "", "pmid": "", "sici": "", "type": "", "title": "", "author": "", "organization": "", "first_published": "", "last_updated": ""}], "types": ["premeditated"]}, {"gva_id": 2002614, "incident_name": "", "start_date": "2021-05-12T20:40Z", "end_date": "", "place_type": "restaurant", "place_name": "Mario's Pizza & Ristorante", "address": "2401 San Pedro Dr NE", "city": "Albuquerque", "state": "NM", "postal_code": "87110", "congressional": 1, "state_senate": 16, "state_house": 25, "deaths": 3, "wounded": 0, "location": {"type": "Point", "coordinates": [35.1057, -106.578]}, "sources": [{"url": "https://www.krqe.com/news/crime/man-linked-to-triple-homicide-arrested/", "isbn": "", "issn": "", "doi": "", "pmid": "", "sici": "", "type": "", "title": "", "author": "", "organization": "", "first_published": "", "last_updated": ""}, {"url": "https://www.abqjournal.com/2389930/apd-investigating-homicide-at-kaseman-hospital.html", "isbn": "", "issn": "", "doi": "", "pmid": "", "sici": "", "type": "", "title": "", "author": "", "organization": "", "first_published": "", "last_updated": ""}, {"url": "https://www.kob.com/albuquerque-news/videos-show-shooting-person-of-interest-in-triple-homicide-investigation/6107123/?cat=500", "isbn": "", "issn": "", "doi": "", "pmid": "", "sici": "", "type": "", "title": "", "author": "", "organization": "", "first_published": "", "last_updated": ""}, {"url": "https://www.abqjournal.com/2390419/security-video-shows-triple-homicide-shooting.html", "isbn": "", "issn": "", "doi": "", "pmid": "", "sici": "", "type": "", "title": "", "author": "", "organization": "", "first_published": "", "last_updated": ""}, {"url": "https://www.kob.com/albuquerque-news/fbi-special-agent-believes-man-arrested-and-three-homicide-victims-all-members-of-aryan-brotherhood/6108981/?cat=516&utm_source=feedburner&utm_medium=feed&utm_campaign=Feed%3A+Kobcom-AlbuquerqueMetro+%28KOB.com+-+Albuq", "isbn": "", "issn": "", "doi": "", "pmid": "", "sici": "", "type": "", "title": "", "author": "", "organization": "", "first_published": "", "last_updated": ""}, {"url": "https://www.kob.com/albuquerque-news/3rd-person-identified-in-kaseman-hospital-triple-homicide/6116100/?cat=500", "isbn": "", "issn": "", "doi": "", "pmid": "", "sici": "", "type": "", "title": "", "author": "", "organization": "", "first_published": "", "last_updated": ""}, {"url": "https://www.justice.gov/usao-nm/pr/previously-convicted-felon-charged-federal-court-firearms-possession", "isbn": "", "issn": "", "doi": "", "pmid": "", "sici": "", "type": "", "title": "", "author": "", "organization": "", "first_published": "", "last_updated": ""}], "types": ["gang violence"]}, {"gva_id": 2002286, "incident_name": "", "start_date": "2021-05-12T06:30Z", "end_date": "", "place_type": "residence", "place_name": "Preston Hills At Mill Creek Apartments", "address": "2910 Buford Dr NE", "city": "Buford", "state": "GA", "postal_code": "30519", "congressional": 7, "state_senate": 45, "state_house": 102, "deaths": 2, "wounded": 2, "location": {"type": "Point", "coordinates": [34.0527, -83.9946]}, "sources": [{"url": "https://www.gwinnettdailypost.com/local/quadruple-shooting-leaves-one-dead-at-buford-area-apartment-complex/article_591ba96c-b31b-11eb-b342-f7ceac7bae6f.html", "isbn": "", "issn": "", "doi": "", "pmid": "", "sici": "", "type": "", "title": "", "author": "", "organization": "", "first_published": "", "last_updated": ""}, {"url": "https://www.ajc.com/news/2-dead-after-quadruple-shooting-at-buford-area-apartments/KPKPV4Q33BDUXJJGKD3MN565BE/", "isbn": "", "issn": "", "doi": "", "pmid": "", "sici": "", "type": "", "title": "", "author": "", "organization": "", "first_published": "", "last_updated": ""}], "types": []}, {"gva_id": 2002526, "incident_name": "", "start_date": "2021-05-11T23:30Z", "end_date": "", "place_type": "residence", "place_name": "", "address": "100 block of Redd Rd", "city": "Orangeburg", "state": "SC", "postal_code": "29118", "congressional": 6, "state_senate": 40, "state_house": 95, "deaths": 2, "wounded": 1, "location": {"type": "Point", "coordinates": [33.5453, -80.9179]}, "sources": [{"url": "https://thetandd.com/news/local/crime-and-courts/two-men-killed-one-injured-in-orangeburg-investigation-continues-into-shootings/article_a9e2fd71-2ecf-56f6-84a8-e6dc848cbcfd.html", "isbn": "", "issn": "", "doi": "", "pmid": "", "sici": "", "type": "", "title": "", "author": "", "organization": "", "first_published": "", "last_updated": ""}, {"url": "https://thetandd.com/news/local/crime-and-courts/orangeburg-county-officials-identify-two-men-shot-killed/article_294c4776-1955-554c-baea-95925bdb1e35.html", "isbn": "", "issn": "", "doi": "", "pmid": "", "sici": "", "type": "", "title": "", "author": "", "organization": "", "first_published": "", "last_updated": ""}], "types": []}, {"gva_id": 2124396, "incident_name": "", "start_date": "2021-09-24", "end_date": "", "place_type": "residence", "place_name": "", "address": "749 Silver Bluff Rd", "city": "Aiken", "state": "SC", "postal_code": "29803", "congressional": 2, "state_senate": 24, "state_house": 81, "deaths": 4, "wounded": 1, "location": {"type": "Point", "coordinates": [33.5149, -81.7306]}, "sources": [{"url": "https://www.augustachronicle.com/story/news/2021/09/24/aiken-county-authorities-investigate-murder-suicide-apartments/5844881001/", "isbn": "", "issn": "", "doi": "", "pmid": "", "sici": "", "type": "", "title": "", "author": "", "organization": "", "first_published": "", "last_updated": ""}, {"url": "https://www.wrdw.com/2021/09/24/4-people-slain-aiken-shooting/", "isbn": "", "issn": "", "doi": "", "pmid": "", "sici": "", "type": "", "title": "", "author": "", "organization": "", "first_published": "", "last_updated": ""}], "types": ["murder-suicide"]}, {"gva_id": 2123395, "incident_name": "", "start_date": "2021-09-23", "end_date": "", "place_type": "store", "place_name": "", "address": "240 New Byhalia Rd", "city": "Collierville", "state": "TN", "postal_code": "38017", "congressional": 8, "state_senate": 32, "state_house": 95, "deaths": 2, "wounded": 14, "location": {"type": "Point", "coordinates": [35.0487, -89.6885]}, "sources": [{"url": "https://www.fox13memphis.com/news/local/active-shooter-reported-collierville-kroger-officials-say/K4VFTTAFN5GMRBFAHRULX25KUM/?utm_campaign=snd-autopilot", "isbn": "", "issn": "", "doi": "", "pmid": "", "sici": "", "type": "", "title": "", "author": "", "organization": "", "first_published": "", "last_updated": ""}, {"url": "https://www.wsmv.com/news/reports-multiple-people-shot-at-kroger-near-memphis/article_926ca246-1ca4-11ec-a115-274f5cc6a047.html", "isbn": "", "issn": "", "doi": "", "pmid": "", "sici": "", "type": "", "title": "", "author": "", "organization": "", "first_published": "", "last_updated": ""}, {"url": "https://www.localmemphis.com/article/news/crime/reports-of-active-shooter-at-kroger-on-new-byhalia-road-in-collierville/522-e03f3483-9dc0-4cc0-9b00-a1a6574d63a5?fbclid=IwAR27vJNccBpuaEAdYTAh3bY0FuDf1SxzvwTLjs69YaeqDBC_X9adN5s2whU", "isbn": "", "issn": "", "doi": "", "pmid": "", "sici": "", "type": "", "title": "", "author": "", "organization": "", "first_published": "", "last_updated": ""}, {"url": " https://www.actionnews5.com/2021/09/23/active-shooting-situation-reported-collierville-schools-sheltering-plac", "isbn": "", "issn": "", "doi": "", "pmid": "", "sici": "", "type": "", "title": "", "author": "", "organization": "", "first_published": "", "last_updated": ""}, {"url": " https://abc7chicago.com/collierville-shooting-kroger-tn-memphis-news/11041589/", "isbn": "", "issn": "", "doi": "", "pmid": "", "sici": "", "type": "", "title": "", "author": "", "organization": "", "first_published": "", "last_updated": ""}], "types": ["murder-suicide"]}, {"gva_id": 2122565, "incident_name": "", "start_date": "2021-09-22", "end_date": "", "place_type": "residence", "place_name": "", "address": "1100 block of Charlie Dr", "city": "Fayetteville", "state": "NC", "postal_code": "28311", "congressional": 8, "state_senate": 21, "state_house": 42, "deaths": 2, "wounded": 2, "location": {"type": "Point", "coordinates": [35.1135, -78.935]}, "sources": [], "types": []}, {"gva_id": 2126261, "incident_name": "", "start_date": "2021-09-26", "end_date": "", "place_type": "bar", "place_name": "La Familia Sports Pub and Lounge", "address": "22855 Pacific Hwy S", "city": "Des Moines", "state": "WA", "postal_code": "98198", "congressional": 9, "state_senate": 33, "state_house": 33, "deaths": 3, "wounded": 3, "location": {"type": "Point", "coordinates": [47.3956, -122.295]}, "sources": [{"url": "https://www.king5.com/article/news/crime/des-moines-la-familia-sports-pub-and-lounge-fatal-shooting/281-d3a02af0-ca4c-4d4d-b5a7-0b6ea41e78f8", "isbn": "", "issn": "", "doi": "", "pmid": "", "sici": "", "type": "", "title": "", "author": "", "organization": "", "first_published": "", "last_updated": ""}, {"url": " https://www.q13fox.com/news/3-killed-3-injured-in-des-moines-bar-shooting", "isbn": "", "issn": "", "doi": "", "pmid": "", "sici": "", "type": "", "title": "", "author": "", "organization": "", "first_published": "", "last_updated": ""}], "types": []}, {"gva_id": 2126212, "incident_name": "", "start_date": "2021-09-26", "end_date": "", "place_type": "residence", "place_name": "", "address": "200 block of W Balview Ave", "city": "Norfolk", "state": "VA", "postal_code": "23503", "congressional": 2, "state_senate": 6, "state_house": 100, "deaths": 2, "wounded": 1, "location": {"type": "Point", "coordinates": [36.9542, -76.2555]}, "sources": [{"url": " https://www.wavy.com/news/local-news/norfolk/2-dead-1-seriously-injured-in-norfolk-shooting/", "isbn": "", "issn": "", "doi": "", "pmid": "", "sici": "", "type": "", "title": "", "author": "", "organization": "", "first_published": "", "last_updated": ""}, {"url": "https://www.13newsnow.com/article/news/crime/shooting-norfolk-home-two-dead-one-injured/291-8cd60d53-2e7e-46dc-b10d-6bb2c3a4b49e", "isbn": "", "issn": "", "doi": "", "pmid": "", "sici": "", "type": "", "title": "", "author": "", "organization": "", "first_published": "", "last_updated": ""}], "types": ["domestic violence"]}, {"gva_id": 2125444, "incident_name": "", "start_date": "2021-09-25", "end_date": "", "place_type": "residence", "place_name": "", "address": "Co Rd 60", "city": "Athens", "state": "TN", "postal_code": "37303", "congressional": 3, "state_senate": 9, "state_house": 23, "deaths": 4, "wounded": 0, "location": {"type": "Point", "coordinates": [35.4211, -84.7418]}, "sources": [{"url": " https://www.wate.com/news/4-dead-10-month-old-missing-after-shooting-in-mcminn-county/", "isbn": "", "issn": "", "doi": "", "pmid": "", "sici": "", "type": "", "title": "", "author": "", "organization": "", "first_published": "", "last_updated": ""}, {"url": " https://www.wbir.com/article/news/crime/mcso-four-dead-and-10-month-old-missing-after-shooting-in-mcminn-co-near-riceville/51-6a2fb042-9d06-4cf4-8449-06df557eea13", "isbn": "", "issn": "", "doi": "", "pmid": "", "sici": "", "type": "", "title": "", "author": "", "organization": "", "first_published": "", "last_updated": ""}], "types": ["domestic violence"]}, {"gva_id": 2120940, "incident_name": "", "start_date": "2021-09-20", "end_date": "", "place_type": "street", "place_name": "", "address": "Broad St and Chew Ave", "city": "Philadelphia", "state": "PA", "postal_code": "19138", "congressional": 3, "state_senate": 4, "state_house": 201, "deaths": 1, "wounded": 5, "location": {"type": "Point", "coordinates": [40.0398, -75.1444]}, "sources": [{"url": " https://6abc.com/philadelphia-shooting-today-fern-rock-pa/11033242/", "isbn": "", "issn": "", "doi": "", "pmid": "", "sici": "", "type": "", "title": "", "author": "", "organization": "", "first_published": "", "last_updated": ""}, {"url": " https://www.myplainview.com/news/article/Police-1-dead-5-wounded-in-drive-by-shooting-16473925.php", "isbn": "", "issn": "", "doi": "", "pmid": "", "sici": "", "type": "", "title": "", "author": "", "organization": "", "first_published": "", "last_updated": ""}, {"url": " https://www.nbcphiladelphia.com/news/local/6-shot-in-philadelphias-fern-rock-neighborhood/2965209/", "isbn": "", "issn": "", "doi": "", "pmid": "", "sici": "", "type": "", "title": "", "author": "", "organization": "", "first_published": "", "last_updated": ""}, {"url": " https://philadelphia.cbslocal.com/2021/09/20/philadelphia-shooting-olney-broad-street-chew-avenue-police/", "isbn": "", "issn": "", "doi": "", "pmid": "", "sici": "", "type": "", "title": "", "author": "", "organization": "", "first_published": "", "last_updated": ""}, {"url": " https://www.fox29.com/news/6-shot-1-killed-after-fern-rock-drive-by-shooting-police-say\n", "isbn": "", "issn": "", "doi": "", "pmid": "", "sici": "", "type": "", "title": "", "author": "", "organization": "", "first_published": "", "last_updated": ""}, {"url": " https://6abc.com/philadelphia-shooting-today-fern-rock-pa/11035629/", "isbn": "", "issn": "", "doi": "", "pmid": "", "sici": "", "type": "", "title": "", "author": "", "organization": "", "first_published": "", "last_updated": ""}], "types": []}, {"gva_id": 2119583, "incident_name": "", "start_date": "2021-09-19", "end_date": "", "place_type": "residence", "place_name": "", "address": "300 block of Driving Park Ave", "city": "Rochester", "state": "NY", "postal_code": "14613", "congressional": 25, "state_senate": 56, "state_house": 136, "deaths": 2, "wounded": 2, "location": {"type": "Point", "coordinates": [43.1811, -77.638]}, "sources": [{"url": " https://13wham.com/news/local/two-killed-two-injured-in-driving-park-avenue-shooting", "isbn": "", "issn": "", "doi": "", "pmid": "", "sici": "", "type": "", "title": "", "author": "", "organization": "", "first_published": "", "last_updated": ""}, {"url": " https://www.whec.com/rochester-new-york-news/presumptive-mayor-elect-malik-evans-on-quadruple-shooting-on-driving-park-avenue/6242900/", "isbn": "", "issn": "", "doi": "", "pmid": "", "sici": "", "type": "", "title": "", "author": "", "organization": "", "first_published": "", "last_updated": ""}, {"url": " https://www.whec.com/rochester-new-york-news/rpd-2-dead-2-injured-in-shooting-on-driving-park/6242637/?cat=565", "isbn": "", "issn": "", "doi": "", "pmid": "", "sici": "", "type": "", "title": "", "author": "", "organization": "", "first_published": "", "last_updated": ""}, {"url": ": https://www.democratandchronicle.com/story/news/2021/09/20/driving-park-ave-shooing-rochester-ny-what-we-know-now/8416605002/", "isbn": "", "issn": "", "doi": "", "pmid": "", "sici": "", "type": "", "title": "", "author": "", "organization": "", "first_published": "", "last_updated": ""}], "types": []}, {"gva_id": 2001682, "incident_name": "", "start_date": "2021-05-10T02:50Z", "end_date": "", "place_type": "residence", "place_name": "", "address": "700 block of Lehigh St", "city": "Allentown", "state": "PA", "postal_code": "18103", "congressional": 7, "state_senate": 16, "state_house": 22, "deaths": 1, "wounded": 2, "location": {"type": "Point", "coordinates": [40.5936, -75.4673]}, "sources": [{"url": "https://philadelphia.cbslocal.com/2021/05/11/13-year-old-allentown-triple-shooting-lehigh-street/", "isbn": "", "issn": "", "doi": "", "pmid": "", "sici": "", "type": "", "title": "", "author": "", "organization": "", "first_published": "", "last_updated": ""}, {"url": "https://6abc.com/29-year-old-man-shot-and-killed-in-allentown/10613280/", "isbn": "", "issn": "", "doi": "", "pmid": "", "sici": "", "type": "", "title": "", "author": "", "organization": "", "first_published": "", "last_updated": ""}, {"url": "https://www.wfmz.com/news/area/lehighvalley/witness-bullets-flying-as-man-shot-dead-wife-injured-in-allentown/article_8572e374-b251-11eb-b2af-d3b6aac1c6f6.html", "isbn": "", "issn": "", "doi": "", "pmid": "", "sici": "", "type": "", "title": "", "author": "", "organization": "", "first_published": "", "last_updated": ""}], "types": []}, {"gva_id": 1999417, "incident_name": "", "start_date": "2021-05-09T20:30Z", "end_date": "", "place_type": "residence", "place_name": "", "address": "100 block of E Albanus St", "city": "Philadelphia", "state": "PA", "postal_code": "19120", "congressional": 2, "state_senate": 3, "state_house": 179, "deaths": 2, "wounded": 3, "location": {"type": "Point", "coordinates": [40.0266, -75.1233]}, "sources": [{"url": "https://6abc.com/quintuple-shooting-leaves-2-dead-in-philly;-at-least-19-shot-this-weekend/10603708/", "isbn": "", "issn": "", "doi": "", "pmid": "", "sici": "", "type": "", "title": "", "author": "", "organization": "", "first_published": "", "last_updated": ""}, {"url": "https://philadelphia.cbslocal.com/2021/05/09/quintuple-shooting-olney-teen-23-year-old-killed/", "isbn": "", "issn": "", "doi": "", "pmid": "", "sici": "", "type": "", "title": "", "author": "", "organization": "", "first_published": "", "last_updated": ""}], "types": []}, {"gva_id": 1999193, "incident_name": "", "start_date": "2021-05-09T07:30Z", "end_date": "", "place_type": "residence", "place_name": "", "address": "122 N 2nd St", "city": "Phoenix", "state": "AZ", "postal_code": "85004", "congressional": 7, "state_senate": 27, "state_house": 27, "deaths": 1, "wounded": 7, "location": {"type": "Point", "coordinates": [33.4497, -112.072]}, "sources": [{"url": "https://www.cnn.com/2021/05/09/us/phoenix-fatal-shooting/index.html", "isbn": "", "issn": "", "doi": "", "pmid": "", "sici": "", "type": "", "title": "", "author": "", "organization": "", "first_published": "", "last_updated": ""}, {"url": "https://www.12news.com/article/news/crime/1-killed-7-injured-after-shooting-at-phoenix-hyatt-regency-5-9-2021/75-93416320-d310-4076-b1d1-d1c37c89e7dc", "isbn": "", "issn": "", "doi": "", "pmid": "", "sici": "", "type": "", "title": "", "author": "", "organization": "", "first_published": "", "last_updated": ""}, {"url": "https://www.abc15.com/news/region-phoenix-metro/central-phoenix/police-on-scene-of-a-shooting-investigation-at-a-downtown-phoenix-hotel", "isbn": "", "issn": "", "doi": "", "pmid": "", "sici": "", "type": "", "title": "", "author": "", "organization": "", "first_published": "", "last_updated": ""}, {"url": "https://www.kgun9.com/news/local-news/police-identify-man-killed-in-phoenix-hotel-shooting", "isbn": "", "issn": "", "doi": "", "pmid": "", "sici": "", "type": "", "title": "", "author": "", "organization": "", "first_published": "", "last_updated": ""}, {"url": "https://www.azfamily.com/news/survivor-describes-shooting-at-hyatt-regency-hotel-in-downtown-phoenix-that-left-1-dead-7/article_aabce6a0-b0be-11eb-b78b-6f0aee3ff51a.html?block_id=667482", "isbn": "", "issn": "", "doi": "", "pmid": "", "sici": "", "type": "", "title": "", "author": "", "organization": "", "first_published": "", "last_updated": ""}, {"url": "https://www.azcentral.com/story/news/local/phoenix-breaking/2021/05/18/phoenix-police-arrest-2-connection-shooting-downtown-hotel/5061129001/", "isbn": "", "issn": "", "doi": "", "pmid": "", "sici": "", "type": "", "title": "", "author": "", "organization": "", "first_published": "", "last_updated": ""}], "types": []}, {"gva_id": 2126450, "incident_name": "", "start_date": "2021-09-27", "end_date": "", "place_type": "park", "place_name": "", "address": "826 N Ridgeway Ave", "city": "Chicago", "state": "IL", "postal_code": "60651", "congressional": 7, "state_senate": 5, "state_house": 10, "deaths": 1, "wounded": 3, "location": {"type": "Point", "coordinates": [41.8963, -87.7204]}, "sources": [{"url": ": https://twitter.com/Chicago_Scanner/status/1442396373555503104", "isbn": "", "issn": "", "doi": "", "pmid": "", "sici": "", "type": "", "title": "", "author": "", "organization": "", "first_published": "", "last_updated": ""}, {"url": " https://chicago.suntimes.com/crime/2021/9/27/22695938/1-killed-3-wounded-teen-humboldt-park-mass-shooting", "isbn": "", "issn": "", "doi": "", "pmid": "", "sici": "", "type": "", "title": "", "author": "", "organization": "", "first_published": "", "last_updated": ""}], "types": []}, {"gva_id": 1999909, "incident_name": "", "start_date": "2021-05-09T06:15Z", "end_date": "", "place_type": "residence", "place_name": "", "address": "6112 W Afton Pl", "city": "Los Angeles", "state": "CA", "postal_code": "90028", "congressional": 28, "state_senate": 26, "state_house": 50, "deaths": 1, "wounded": 3, "location": {"type": "Point", "coordinates": [34.095, -118.323]}, "sources": [{"url": "https://abc7.com/1-dead-3-others-wounded-in-shooting-in-hollywood/10607173/", "isbn": "", "issn": "", "doi": "", "pmid": "", "sici": "", "type": "", "title": "", "author": "", "organization": "", "first_published": "", "last_updated": ""}, {"url": "https://www.nbclosangeles.com/news/local/one-dead-five-hospitalized-after-hollywood-shooting/2591699/", "isbn": "", "issn": "", "doi": "", "pmid": "", "sici": "", "type": "", "title": "", "author": "", "organization": "", "first_published": "", "last_updated": ""}, {"url": "https://ktla.com/news/local-news/1-killed-5-wounded-in-shooting-at-mothers-day-party-in-hollywood/", "isbn": "", "issn": "", "doi": "", "pmid": "", "sici": "", "type": "", "title": "", "author": "", "organization": "", "first_published": "", "last_updated": ""}, {"url": "https://losangeles.cbslocal.com/2021/05/10/one-man-killed-3-wounded-in-hollywood-shooting/", "isbn": "", "issn": "", "doi": "", "pmid": "", "sici": "", "type": "", "title": "", "author": "", "organization": "", "first_published": "", "last_updated": ""}], "types": []}, {"gva_id": 1999125, "incident_name": "", "start_date": "2021-05-09T06:18Z", "end_date": "", "place_type": "residence", "place_name": "", "address": "2828 Preakness Way", "city": "Colorado Springs", "state": "CO", "postal_code": "80916", "congressional": 5, "state_senate": 11, "state_house": 17, "deaths": 7, "wounded": 0, "location": {"type": "Point", "coordinates": [38.7914, -104.733]}, "sources": [{"url": "https://www.9news.com/article/news/crime/colorado-springs-shooting-multiple-victims/73-428e2525-2e0d-4c6e-a716-6badf26bedea", "isbn": "", "issn": "", "doi": "", "pmid": "", "sici": "", "type": "", "title": "", "author": "", "organization": "", "first_published": "", "last_updated": ""}, {"url": "https://www.kktv.com/2021/05/09/4-including-suspect-killed-in-shooting-at-colorado-springs-mobile-home-community/", "isbn": "", "issn": "", "doi": "", "pmid": "", "sici": "", "type": "", "title": "", "author": "", "organization": "", "first_published": "", "last_updated": ""}, {"url": "https://www.koaa.com/news/covering-colorado/colorado-springs-police-multiple-deceased-victims-found-on-preakness-way", "isbn": "", "issn": "", "doi": "", "pmid": "", "sici": "", "type": "", "title": "", "author": "", "organization": "", "first_published": "", "last_updated": ""}, {"url": "https://gazette.com/news/local/4-killed-in-shooting-at-colorado-springs-mobile-home-community/article_4186ea1a-b0cc-11eb-b3e5-9f195dc56ec0.html", "isbn": "", "issn": "", "doi": "", "pmid": "", "sici": "", "type": "", "title": "", "author": "", "organization": "", "first_published": "", "last_updated": ""}, {"url": "https://coloradosprings.gov/police-department/article/news/update-homicide-investigation-2800-block", "isbn": "", "issn": "", "doi": "", "pmid": "", "sici": "", "type": "", "title": "", "author": "", "organization": "", "first_published": "", "last_updated": ""}, {"url": "https://gazette.com/news/neighbors-in-colorado-springs-mass-shooting-mourn-the-6-slain-identified-by-family-member/article_4c15d008-b1c2-11eb-b8cf-6735c450f9fa.html", "isbn": "", "issn": "", "doi": "", "pmid": "", "sici": "", "type": "", "title": "", "author": "", "organization": "", "first_published": "", "last_updated": ""}], "types": ["premeditated", "murder-suicide"]}, {"gva_id": 1998476, "incident_name": "", "start_date": "2021-05-08T10:40Z", "end_date": "", "place_type": "other", "place_name": "", "address": "7300 block of Maury Rd", "city": "Windsor Mill", "state": "MD", "postal_code": "21244", "congressional": 7, "state_senate": 44, "state_house": 44, "deaths": 3, "wounded": 1, "location": {"type": "Point", "coordinates": [39.3102, -76.7726]}, "sources": [{"url": "https://wjla.com/news/crime/authorities-4-dead-1-hurt-after-shooting-fire-in-maryland", "isbn": "", "issn": "", "doi": "", "pmid": "", "sici": "", "type": "", "title": "", "author": "", "organization": "", "first_published": "", "last_updated": ""}, {"url": "https://www.wbaltv.com/article/woodlawn-fire-police-activity/36371512#", "isbn": "", "issn": "", "doi": "", "pmid": "", "sici": "", "type": "", "title": "", "author": "", "organization": "", "first_published": "", "last_updated": ""}], "types": []}, {"gva_id": 1998830, "incident_name": "", "start_date": "2021-05-08T22:00Z", "end_date": "", "place_type": "residence", "place_name": "", "address": "718 Florence Ave", "city": "Lexington", "state": "KY", "postal_code": "40508", "congressional": 6, "state_senate": 13, "state_house": 77, "deaths": 1, "wounded": 2, "location": {"type": "Point", "coordinates": [38.0662, -84.5063]}, "sources": [{"url": "https://www.lex18.com/news/covering-kentucky/heavy-police-response-in-lexington", "isbn": "", "issn": "", "doi": "", "pmid": "", "sici": "", "type": "", "title": "", "author": "", "organization": "", "first_published": "", "last_updated": ""}, {"url": "https://www.wkyt.com/2021/05/08/two-men-and-a-child-injured-in-shooting-on-florence-avenue/", "isbn": "", "issn": "", "doi": "", "pmid": "", "sici": "", "type": "", "title": "", "author": "", "organization": "", "first_published": "", "last_updated": ""}], "types": []}, {"gva_id": 1998888, "incident_name": "", "start_date": "2021-05-08T08:00Z", "end_date": "", "place_type": "nightclub", "place_name": "Club 81", "address": "70201 US-51", "city": "Tangipahoa", "state": "LA", "postal_code": "70456", "congressional": 5, "state_senate": 12, "state_house": 72, "deaths": 1, "wounded": 2, "location": {"type": "Point", "coordinates": [30.8754, -90.5119]}, "sources": [{"url": "https://www.wafb.com/2021/05/08/police-shot-killed-tangipahoa-parish-nightclub-early-saturday/", "isbn": "", "issn": "", "doi": "", "pmid": "", "sici": "", "type": "", "title": "", "author": "", "organization": "", "first_published": "", "last_updated": ""}, {"url": "https://www.facebook.com/permalink.php?story_fbid=4274690532584606&id=119215974798770", "isbn": "", "issn": "", "doi": "", "pmid": "", "sici": "", "type": "", "title": "", "author": "", "organization": "", "first_published": "", "last_updated": ""}, {"url": "https://www.hammondstar.com/news/shooting-at-club-81-leaves-1-dead-2-wounded/article_088a27c1-de2a-535c-b63d-f639eb2daac2.html", "isbn": "", "issn": "", "doi": "", "pmid": "", "sici": "", "type": "", "title": "", "author": "", "organization": "", "first_published": "", "last_updated": ""}], "types": []}, {"gva_id": 1998115, "incident_name": "", "start_date": "2021-05-07T04:24Z", "end_date": "", "place_type": "other", "place_name": "", "address": "Parkway Blvd and N George St", "city": "York", "state": "PA", "postal_code": "17404", "congressional": 10, "state_senate": 28, "state_house": 47, "deaths": 1, "wounded": 2, "location": {"type": "Point", "coordinates": [39.9714, -76.7318]}, "sources": [{"url": "https://www.pennlive.com/news/2021/05/man-killed-in-york-city-triple-shooting-idd.html", "isbn": "", "issn": "", "doi": "", "pmid": "", "sici": "", "type": "", "title": "", "author": "", "organization": "", "first_published": "", "last_updated": ""}, {"url": "https://www.fox43.com/article/news/crime/police-scene-york-city-shooting/521-4f21c97c-0bb7-4c54-a99a-23cdf88925ca", "isbn": "", "issn": "", "doi": "", "pmid": "", "sici": "", "type": "", "title": "", "author": "", "organization": "", "first_published": "", "last_updated": ""}, {"url": "https://www.yorkdispatch.com/story/news/2021/05/07/one-killed-2-shot-overnight-shooting-york-city/4986177001/", "isbn": "", "issn": "", "doi": "", "pmid": "", "sici": "", "type": "", "title": "", "author": "", "organization": "", "first_published": "", "last_updated": ""}], "types": []}, {"gva_id": 1998042, "incident_name": "", "start_date": "2021-05-07T19:30Z", "end_date": "", "place_type": "other", "place_name": "", "address": "800 block of Briar Ln", "city": "Oklahoma City", "state": "OK", "postal_code": "73102", "congressional": 5, "state_senate": 46, "state_house": 92, "deaths": 1, "wounded": 2, "location": {"type": "Point", "coordinates": [35.4676, -97.5164]}, "sources": [{"url": "https://kfor.com/news/local/1-man-dead-2-injured-following-shooting-in-del-city/", "isbn": "", "issn": "", "doi": "", "pmid": "", "sici": "", "type": "", "title": "", "author": "", "organization": "", "first_published": "", "last_updated": ""}, {"url": "https://kfor.com/news/local/police-searching-for-suv-in-connection-to-deadly-drive-by-shooting-in-del-city/", "isbn": "", "issn": "", "doi": "", "pmid": "", "sici": "", "type": "", "title": "", "author": "", "organization": "", "first_published": "", "last_updated": ""}], "types": []}, {"gva_id": 1998067, "incident_name": "", "start_date": "2021-05-07T23:26Z", "end_date": "", "place_type": "park", "place_name": "Kinloch Park", "address": "5541 Mable Ave", "city": "Saint Louis", "state": "MO", "postal_code": "63140", "congressional": 1, "state_senate": 14, "state_house": 73, "deaths": 2, "wounded": 3, "location": {"type": "Point", "coordinates": [38.7344, -90.3203]}, "sources": [{"url": "https://www.ksdk.com/article/news/crime/2-men-fatally-shot-3-wounded-in-kinloch-self-transported-area-hospitals/63-4b5d2fc5-0285-47bc-9648-8601bbe94f58", "isbn": "", "issn": "", "doi": "", "pmid": "", "sici": "", "type": "", "title": "", "author": "", "organization": "", "first_published": "", "last_updated": ""}, {"url": "https://www.stltoday.com/news/local/crime-and-courts/2-men-killed-after-shooting-in-kinloch/article_9d21393a-69fb-52d8-ae14-93467a27bbb9.html", "isbn": "", "issn": "", "doi": "", "pmid": "", "sici": "", "type": "", "title": "", "author": "", "organization": "", "first_published": "", "last_updated": ""}, {"url": "https://www.kmov.com/news/2-killed-3-injured-after-shots-fired-at-north-county-park/article_fbdbf236-af94-11eb-a950-ebe0268f9680.html", "isbn": "", "issn": "", "doi": "", "pmid": "", "sici": "", "type": "", "title": "", "author": "", "organization": "", "first_published": "", "last_updated": ""}], "types": []}, {"gva_id": 1993551, "incident_name": "", "start_date": "2021-05-03T05:45Z", "end_date": "", "place_type": "residence", "place_name": "", "address": "1315 Randolph St", "city": "Saginaw", "state": "MI", "postal_code": "48601", "congressional": 5, "state_senate": 32, "state_house": 95, "deaths": 1, "wounded": 4, "location": {"type": "Point", "coordinates": [43.4033, -83.9476]}, "sources": [{"url": "https://www.mlive.com/news/saginaw-bay-city/2021/05/man-dead-after-5-people-shot-during-party-at-house-operating-as-unregistered-airbnb-in-saginaw.html", "isbn": "", "issn": "", "doi": "", "pmid": "", "sici": "", "type": "", "title": "", "author": "", "organization": "", "first_published": "", "last_updated": ""}, {"url": "https://www.mlive.com/news/saginaw-bay-city/2021/05/police-release-name-of-saginaw-man-killed-during-party-at-daily-rental-house.html", "isbn": "", "issn": "", "doi": "", "pmid": "", "sici": "", "type": "", "title": "", "author": "", "organization": "", "first_published": "", "last_updated": ""}], "types": []}, {"gva_id": 1993057, "incident_name": "", "start_date": "2021-05-02", "end_date": "", "place_type": "residence", "place_name": "", "address": "12900 SW 191 Ter", "city": "Miami", "state": "FL", "postal_code": "33177", "congressional": 26, "state_senate": 40, "state_house": 120, "deaths": 2, "wounded": 1, "location": {"type": "Point", "coordinates": [25.5883, -80.4014]}, "sources": [{"url": "https://www.local10.com/news/local/2021/05/03/3-dead-after-shooting-inside-home-in-southwest-miami-dade/", "isbn": "", "issn": "", "doi": "", "pmid": "", "sici": "", "type": "", "title": "", "author": "", "organization": "", "first_published": "", "last_updated": ""}, {"url": "https://wsvn.com/news/local/miami-dade/shooter-2-women-dead-after-man-barricades-self-inside-sw-miami-dade-home/", "isbn": "", "issn": "", "doi": "", "pmid": "", "sici": "", "type": "", "title": "", "author": "", "organization": "", "first_published": "", "last_updated": ""}, {"url": "https://www.nbcmiami.com/news/local/3-people-found-dead-after-shooting-at-miami-dade-home/2442001/", "isbn": "", "issn": "", "doi": "", "pmid": "", "sici": "", "type": "", "title": "", "author": "", "organization": "", "first_published": "", "last_updated": ""}, {"url": "https://www.local10.com/news/local/2021/05/04/more-details-emerge-about-killings-in-miami-dade-home/", "isbn": "", "issn": "", "doi": "", "pmid": "", "sici": "", "type": "", "title": "", "author": "", "organization": "", "first_published": "", "last_updated": ""}], "types": ["domestic violence", "murder-suicide"]}, {"gva_id": 1993221, "incident_name": "", "start_date": "2021-05-02T00:11Z", "end_date": "", "place_type": "park", "place_name": "Carroll Park", "address": "1500 block of Washington Blvd", "city": "Baltimore", "state": "MD", "postal_code": "21230", "congressional": 3, "state_senate": 40, "state_house": 40, "deaths": 1, "wounded": 3, "location": {"type": "Point", "coordinates": [39.279, -76.643]}, "sources": [{"url": "https://www.wbaltv.com/article/quadruple-shooting-carroll-park-baltimore/36313317", "isbn": "", "issn": "", "doi": "", "pmid": "", "sici": "", "type": "", "title": "", "author": "", "organization": "", "first_published": "", "last_updated": ""}], "types": []}, {"gva_id": 1993664, "incident_name": "", "start_date": "2021-05-02T03:00Z", "end_date": "", "place_type": "residence", "place_name": "", "address": "5200 block of Burton St", "city": "Philadelphia", "state": "PA", "postal_code": "19124", "congressional": 2, "state_senate": 2, "state_house": 179, "deaths": 1, "wounded": 3, "location": {"type": "Point", "coordinates": [40.015, -75.071]}, "sources": [{"url": "https://philadelphia.cbslocal.com/2021/05/03/burton-street-quadruple-shooting-frankford/", "isbn": "", "issn": "", "doi": "", "pmid": "", "sici": "", "type": "", "title": "", "author": "", "organization": "", "first_published": "", "last_updated": ""}], "types": []}, {"gva_id": 1992469, "incident_name": "", "start_date": "2021-05-01T01:30Z", "end_date": "", "place_type": "other", "place_name": "", "address": "1117 Harlem Academy Ave", "city": "Clewiston", "state": "FL", "postal_code": "33440", "congressional": 25, "state_senate": 28, "state_house": 80, "deaths": 1, "wounded": 3, "location": {"type": "Point", "coordinates": [26.7377, -80.9536]}, "sources": [{"url": "https://www.winknews.com/2021/05/02/shooting-reported-at-festival-in-clewiston/", "isbn": "", "issn": "", "doi": "", "pmid": "", "sici": "", "type": "", "title": "", "author": "", "organization": "", "first_published": "", "last_updated": ""}, {"url": "https://www.facebook.com/hendrysheriff/posts/5478232062219411", "isbn": "", "issn": "", "doi": "", "pmid": "", "sici": "", "type": "", "title": "", "author": "", "organization": "", "first_published": "", "last_updated": ""}, {"url": "https://www.winknews.com/2021/05/03/one-young-woman-killed-three-others-injured-after-festival-shooting-in-clewiston/", "isbn": "", "issn": "", "doi": "", "pmid": "", "sici": "", "type": "", "title": "", "author": "", "organization": "", "first_published": "", "last_updated": ""}], "types": []}, {"gva_id": 1992534, "incident_name": "", "start_date": "2021-05-01T04:40Z", "end_date": "", "place_type": "other", "place_name": "", "address": "St Bernard Ave and N Claiborne Ave", "city": "New Orleans", "state": "LA", "postal_code": "70116", "congressional": 2, "state_senate": 5, "state_house": 93, "deaths": 2, "wounded": 3, "location": {"type": "Point", "coordinates": [29.9726, -90.0655]}, "sources": [{"url": "https://www.nola.com/news/crime_police/article_3d65ae5e-ab26-11eb-9dcd-e71dff1511b1.html?2346&utm_medium=social&utm_source=twitternoladotcom&utm_campaign=snd", "isbn": "", "issn": "", "doi": "", "pmid": "", "sici": "", "type": "", "title": "", "author": "", "organization": "", "first_published": "", "last_updated": ""}], "types": []}, {"gva_id": 1994893, "incident_name": "", "start_date": "2021-05-04T22:20Z", "end_date": "", "place_type": "other", "place_name": "", "address": "19 Norwich St", "city": "Hartford", "state": "CT", "postal_code": "61060", "congressional": 1, "state_senate": 1, "state_house": 4, "deaths": 1, "wounded": 2, "location": {"type": "Point", "coordinates": [41.7563, -72.6713]}, "sources": [{"url": "https://www.courant.com/breaking-news/hc-br-triple-shooting-hartford-20210504-tqqrafbdqrdvddr7hnx3avf2ui-story.html", "isbn": "", "issn": "", "doi": "", "pmid": "", "sici": "", "type": "", "title": "", "author": "", "organization": "", "first_published": "", "last_updated": ""}, {"url": "https://www.wtnh.com/news/connecticut/hartford/hartford-pd-investigating-triple-shooting-on-norwich-street/", "isbn": "", "issn": "", "doi": "", "pmid": "", "sici": "", "type": "", "title": "", "author": "", "organization": "", "first_published": "", "last_updated": ""}], "types": []}, {"gva_id": 1995232, "incident_name": "", "start_date": "2021-05-04", "end_date": "", "place_type": "other", "place_name": "", "address": "Lindon Ave and Oakland Street", "city": "Shreveport", "state": "LA", "postal_code": "71108", "congressional": 4, "state_senate": 39, "state_house": 3, "deaths": 2, "wounded": 1, "location": {"type": "Point", "coordinates": [32.4586, -93.763]}, "sources": [{"url": "https://www.gunviolencearchive.org/incident/1995232?__cf_chl_jschl_tk__=995b39a3cfb3617f7a34f787258cf8f590776eeb-1623754948-0-AQlbaLyeV_oY_b2Yk2EP9LiE74hNGbkvgwcdAZBlJnbwHU-56UKbUEis8KJsR_F7ZCJm3Z7p34xXHAAAH0fuoY0uYtuaT6YCK6vxAUZZMwuCJwNgNEu-MJGVPOywfMpPPm_96zMsLxwBniMflfy2fqzD9w6ZwtowSPTTLaSYvT5CwVi4Iq7NEy6Fws--CE9UGjqRdgL15Edy9H_AoB_qJ75srZ1qEPAM6TNWab55AUdGfd3kS9E-X8F2o7CKifIMGtyDC8M8CK1B5ACI0EdSRv6_F2qjN2lBafAWTdwEN9wBoqDTpRWo3JhqObJdSx6r_E3wQj_7YZ_43qm5U4Cadx0l-uv6Sf4LFffgvHKliQYsnBAFGxeaGn5H6I0Kgebj7RKNCPorfPWRIiuSoYBFkoGHc_dyWJva94NnG3jQAmEt", "isbn": "", "issn": "", "doi": "", "pmid": "", "sici": "", "type": "", "title": "", "author": "", "organization": "", "first_published": "", "last_updated": ""}], "types": ["murder-suicide"]}, {"gva_id": 1993617, "incident_name": "", "start_date": "2021-05-03", "end_date": "", "place_type": "other", "place_name": "", "address": "2000 Block of Richland Street", "city": "Shreveport", "state": "LA", "postal_code": "70808", "congressional": 6, "state_senate": 16, "state_house": 68, "deaths": 4, "wounded": 1, "location": {"type": "Point", "coordinates": [30.43, -91.1481]}, "sources": [{"url": "https://www.gunviolencearchive.org/incident/1993617", "isbn": "", "issn": "", "doi": "", "pmid": "", "sici": "", "type": "", "title": "", "author": "", "organization": "", "first_published": "", "last_updated": ""}], "types": ["murder-suicide", "domestic violence"]}, {"gva_id": 1993455, "incident_name": "", "start_date": "2021-05-03T08:00Z", "end_date": "", "place_type": "bar", "place_name": "Gringo's Mariscos and Beer", "address": "4209 W Washington Blvd", "city": "Los Angeles", "state": "CA", "postal_code": "90016", "congressional": 37, "state_senate": 30, "state_house": 54, "deaths": 2, "wounded": 1, "location": {"type": "Point", "coordinates": [34.0402, -118.332]}, "sources": [{"url": "https://mynewsla.com/crime/2021/05/03/two-men-shot-to-death-woman-wounded-in-arlington-heights-2/", "isbn": "", "issn": "", "doi": "", "pmid": "", "sici": "", "type": "", "title": "", "author": "", "organization": "", "first_published": "", "last_updated": ""}, {"url": "https://ktla.com/news/local-news/restaurant-altercation-likely-led-to-shooting-that-left-2-dead-1-injured-in-mid-city-neighborhood-lapd/", "isbn": "", "issn": "", "doi": "", "pmid": "", "sici": "", "type": "", "title": "", "author": "", "organization": "", "first_published": "", "last_updated": ""}, {"url": "https://mynewsla.com/crime/2021/05/05/officials-id-two-men-killed-in-shooting-at-strip-mall-in-arlington-heights/", "isbn": "", "issn": "", "doi": "", "pmid": "", "sici": "", "type": "", "title": "", "author": "", "organization": "", "first_published": "", "last_updated": ""}], "types": []}, {"gva_id": 1992193, "incident_name": "", "start_date": "2021-05-01T10:30Z", "end_date": "", "place_type": "residence", "place_name": "", "address": "1641 CR 5675", "city": "Huntsville", "state": "AR", "postal_code": "72740", "congressional": 4, "state_senate": 5, "state_house": 82, "deaths": 2, "wounded": 1, "location": {"type": "Point", "coordinates": [35.9927, -93.7106]}, "sources": [{"url": "https://www.nwahomepage.com/northwest-arkansas-news/2-dead-in-madison-county-homicide-one-wounded-asp-arrests-suspect/", "isbn": "", "issn": "", "doi": "", "pmid": "", "sici": "", "type": "", "title": "", "author": "", "organization": "", "first_published": "", "last_updated": ""}, {"url": "https://www.arkansasonline.com/news/2021/may/02/2-dead-1-injured-in-nw-shooting/", "isbn": "", "issn": "", "doi": "", "pmid": "", "sici": "", "type": "", "title": "", "author": "", "organization": "", "first_published": "", "last_updated": ""}], "types": ["domestic violence"]}, {"gva_id": 1992320, "incident_name": "", "start_date": "2021-05-01", "end_date": "", "place_type": "other", "place_name": "", "address": "860 Glenwood Ave SE", "city": "Atlanta", "state": "GA", "postal_code": "30316", "congressional": 5, "state_senate": 36, "state_house": 59, "deaths": 1, "wounded": 1, "location": {"type": "Point", "coordinates": [33.7407, -84.3603]}, "sources": [{"url": "https://www.gunviolencearchive.org/incident/1992320", "isbn": "", "issn": "", "doi": "", "pmid": "", "sici": "", "type": "", "title": "", "author": "", "organization": "", "first_published": "", "last_updated": ""}, {"url": "https://www.ajc.com/news/breaking-arrest-made-in-15-year-old-girls-shooting-death/4PZUXD6E6NAHZMO3U4S3Z5EGJY/", "isbn": "", "issn": "", "doi": "", "pmid": "", "sici": "", "type": "", "title": "", "author": "", "organization": "", "first_published": "", "last_updated": ""}], "types": ["murder-suicide"]}, {"gva_id": 1992281, "incident_name": "", "start_date": "2021-05-04", "end_date": "", "place_type": "other", "place_name": "Radisson Hotel & Conference Center Green Bay", "address": "2040 Airport Dr", "city": "Green Bay", "state": "WI", "postal_code": "54313", "congressional": 8, "state_senate": 2, "state_house": 4, "deaths": 3, "wounded": 1, "location": {"type": "Point", "coordinates": [44.4979, -88.1228]}, "sources": [{"url": "https://www.wearegreenbay.com/news/local-news/happening-now-active-situation-at-oneida-casino/ ", "isbn": "", "issn": "", "doi": "", "pmid": "", "sici": "", "type": "", "title": "", "author": "", "organization": "", "first_published": "", "last_updated": ""}, {"url": "https://www.gunviolencearchive.org/incident/1992281?__cf_chl_jschl_tk__=80989f482566267f3386066c94eb53e6333d03e5-1624494572-0-AQmvc99zYW6eOaImn-w_hbTLTg8xpTiaTboM3vHCP9F5hHrlFoAn_LHgjsVVnLia7Gv5e4N837zcdfUwCHH8Jkr8eaWkuOaVM7QRNP2T5eVAp0GJ3nWEHbN-4_WCOPvDvFMoFnA2erm6IZwpAJVVqN6Jl_jt187DPqAGkvIvWpgz8BbrHyYaMRbSgQi5l4bSJ_YPZpuZ-ygatbvmqeq33E3ssWYb02fhTXpwmUnIXSNDWp2mmcvndSLUy4iBjvXzsvpPuV2OA_LyMSI8S0C36Rbg1NENhkk5MRUnMucc-IxbUigb39pQxKVrRNQJmDU5ckz2j0S3EYvo7uMhcXiQh6FghlviZbEZjuyned2sg9wR9-gwf1fxoECdwE6z3y6B0feEQEOxA3aUPaWrMux2CNmKj7G9gKLAoV9Fd_AUS2nv", "isbn": "", "issn": "", "doi": "", "pmid": "", "sici": "", "type": "", "title": "", "author": "", "organization": "", "first_published": "", "last_updated": ""}], "types": ["murder-suicide"]}, {"gva_id": 1992410, "incident_name": "", "start_date": "2021-05-01", "end_date": "", "place_type": "other", "place_name": "", "address": "Horton Ave and Brook St", "city": "New Rochelle", "state": "NY", "postal_code": "10801", "congressional": 16, "state_senate": 35, "state_house": 88, "deaths": 1, "wounded": 4, "location": {"type": "Point", "coordinates": [40.9199, -73.7891]}, "sources": [{"url": "https://www.gunviolencearchive.org/incident/1992410", "isbn": "", "issn": "", "doi": "", "pmid": "", "sici": "", "type": "", "title": "", "author": "", "organization": "", "first_published": "", "last_updated": ""}], "types": ["murder-suicide"]}, {"gva_id": 1990821, "incident_name": "", "start_date": "2021-04-29", "end_date": "", "place_type": "residence", "place_name": "", "address": "2300 block of Polar Rock Terrace SW", "city": "Atlanta", "state": "GA", "postal_code": "30315", "congressional": 5, "state_senate": 36, "state_house": 59, "deaths": 1, "wounded": 5, "location": {"type": "Point", "coordinates": [33.6916, -84.3945]}, "sources": [{"url": "https://www.gunviolencearchive.org/incident/1990821", "isbn": "", "issn": "", "doi": "", "pmid": "", "sici": "", "type": "", "title": "", "author": "", "organization": "", "first_published": "", "last_updated": ""}], "types": ["murder-suicide"]}, {"gva_id": 1990680, "incident_name": "", "start_date": "2021-04-29", "end_date": "", "place_type": "other", "place_name": "", "address": "900 block of Market St", "city": "San Francisco", "state": "CA", "postal_code": "94101", "congressional": 12, "state_senate": 11, "state_house": 17, "deaths": 1, "wounded": 2, "location": {"type": "Point", "coordinates": [37.7822, -122.41]}, "sources": [{"url": "https://www.gunviolencearchive.org/incident/1990680", "isbn": "", "issn": "", "doi": "", "pmid": "", "sici": "", "type": "", "title": "", "author": "", "organization": "", "first_published": "", "last_updated": ""}], "types": ["murder-suicide"]}, {"gva_id": 1989840, "incident_name": "", "start_date": "2021-04-28", "end_date": "", "place_type": "residence", "place_name": "", "address": "553 Hardaman Cir", "city": "Boone", "state": "NC", "postal_code": "28607", "congressional": 5, "state_senate": 45, "state_house": 93, "deaths": 4, "wounded": 0, "location": {"type": "Point", "coordinates": [36.2124, -81.6043]}, "sources": [{"url": "https://www.gunviolencearchive.org/incident/1989840", "isbn": "", "issn": "", "doi": "", "pmid": "", "sici": "", "type": "", "title": "", "author": "", "organization": "", "first_published": "", "last_updated": ""}], "types": []}, {"gva_id": 1988252, "incident_name": "", "start_date": "2021-04-27", "end_date": "", "place_type": "highway", "place_name": "California State Route 91", "address": "CA-91", "city": "Fullerton", "state": "CA", "postal_code": "92833", "congressional": 39, "state_senate": 29, "state_house": 65, "deaths": 2, "wounded": 1, "location": {"type": "Point", "coordinates": [33.8543, -117.922]}, "sources": [{"url": "https://www.gunviolencearchive.org/incident/1988252", "isbn": "", "issn": "", "doi": "", "pmid": "", "sici": "", "type": "", "title": "", "author": "", "organization": "", "first_published": "", "last_updated": ""}], "types": []}, {"gva_id": 1988688, "incident_name": "", "start_date": "2021-04-27", "end_date": "", "place_type": "residence", "place_name": "The Belt Atlantic Apartments", "address": "4000 Midlothian Turnpike", "city": "Richmond", "state": "VA", "postal_code": "23224", "congressional": 4, "state_senate": 16, "state_house": 69, "deaths": 2, "wounded": 3, "location": {"type": "Point", "coordinates": [37.5084, -77.4799]}, "sources": [{"url": "https://www.gunviolencearchive.org/incident/1988688", "isbn": "", "issn": "", "doi": "", "pmid": "", "sici": "", "type": "", "title": "", "author": "", "organization": "", "first_published": "", "last_updated": ""}], "types": []}, {"gva_id": 1989096, "incident_name": "", "start_date": "2021-04-27", "end_date": "", "place_type": "residence", "place_name": "", "address": "55 William Sands Jr Rd", "city": "Springfield", "state": "MA", "postal_code": "01109", "congressional": 1, "state_senate": 3, "state_house": 110, "deaths": 1, "wounded": 2, "location": {"type": "Point", "coordinates": [42.132, -72.5357]}, "sources": [{"url": "https://www.gunviolencearchive.org/incident/1989096", "isbn": "", "issn": "", "doi": "", "pmid": "", "sici": "", "type": "", "title": "", "author": "", "organization": "", "first_published": "", "last_updated": ""}], "types": []}]